eneru/__init__.py
eneru/__main__.py
eneru/actions.py
eneru/cli.py
eneru/config.py
eneru/logger.py
eneru/monitor.py
eneru/notifications.py
eneru/state.py
eneru/utils.py
eneru/version.py
eneru-4.10.dist-info/licenses/LICENSE
eneru-4.10.dist-info/METADATA
eneru-4.10.dist-info/WHEEL
eneru-4.10.dist-info/entry_points.txt
eneru-4.10.dist-info/top_level.txt
eneru-4.10.dist-info/RECORD
