Metadata-Version: 2.4
Name: eneru
Version: 4.10
Summary: Intelligent UPS Monitoring & Shutdown Orchestration for NUT
Author-email: Eneru Maintainers <noreply@github.com>
License: MIT
Project-URL: Homepage, https://github.com/m4r1k/Eneru
Project-URL: Documentation, https://eneru.readthedocs.io/latest/
Project-URL: Repository, https://github.com/m4r1k/Eneru.git
Project-URL: Issues, https://github.com/m4r1k/Eneru/issues
Project-URL: Changelog, https://github.com/m4r1k/Eneru/blob/main/CHANGELOG.md
Keywords: ups,nut,monitoring,shutdown,power,infrastructure
Classifier: Development Status :: 5 - Production/Stable
Classifier: Environment :: Console
Classifier: Intended Audience :: System Administrators
Classifier: License :: OSI Approved :: MIT License
Classifier: Operating System :: POSIX :: Linux
Classifier: Programming Language :: Python :: 3
Classifier: Programming Language :: Python :: 3.9
Classifier: Programming Language :: Python :: 3.10
Classifier: Programming Language :: Python :: 3.11
Classifier: Programming Language :: Python :: 3.12
Classifier: Programming Language :: Python :: 3.13
Classifier: Programming Language :: Python :: 3.14
Classifier: Topic :: System :: Monitoring
Classifier: Topic :: System :: Power (UPS)
Classifier: Topic :: System :: Systems Administration
Requires-Python: >=3.9
License-File: LICENSE
Requires-Dist: PyYAML>=5.4.1
Provides-Extra: notifications
Requires-Dist: apprise>=1.9.6; extra == "notifications"
Provides-Extra: dev
Requires-Dist: pytest>=7.0.0; extra == "dev"
Requires-Dist: pytest-cov>=4.0.0; extra == "dev"
Requires-Dist: pytest-mock>=3.10.0; extra == "dev"
Requires-Dist: pytest-timeout>=2.1.0; extra == "dev"
Requires-Dist: apprise>=1.9.6; extra == "dev"
Provides-Extra: docs
Requires-Dist: mkdocs>=1.6.1; extra == "docs"
Requires-Dist: mkdocs-material>=9.7.1; extra == "docs"
Dynamic: license-file
